Workbook

Sheet Lisez-moi
A1: GESTION DES DONS — LES PETITS ENFANTS DE MARIE
A2: Mode d'emploi du classeur : remplissez uniquement les cellules JAUNES. Tout ce qui est blanc se calcule automatiquement. Chaque onglet contient une ligne d'exemple à remplacer par vos vraies données.
A4: Trésorerie | B4: Le journal de tous les mouvements : dons reçus et dépenses, ligne par ligne, avec la campagne, la catégorie, le n° de facture et le solde automatique. Les dépenses se saisissent en € ou en FCFA, la conversion est automatique.
A5: Synthèse | B5: L'analyse comparative par campagne : saisissez le montant total envoyé à la logistique (colonne jaune), le tableau le compare aux dons reçus et aux factures justifiées, et calcule le reste à justifier — avec la clôture de l'année en bas.
A6: Budget | B6: Votre budget par poste de dépense, modifiable à tout moment. Le « dépensé réel » se calcule tout seul depuis l'onglet Trésorerie.
A7: Prix | B7: Le comparatif des prix des articles d'une campagne à l'autre, pour analyser l'évolution des prix (riz, cahiers, cartables…).
A8: Dons | B8: Le détail des articles donnés à chaque orphelinat, campagne par campagne : article, quantité, valeur.
A9: Listes | B9: Vos campagnes, catégories de dépenses et le taux de change €/FCFA : modifiez-les ici, ils alimentent tous les onglets.
A11: Astuce : à chaque nouvelle campagne, ajoutez simplement son nom dans l'onglet Listes.

Sheet Trésorerie
A1: SUIVI DE TRÉSORERIE
A2: Une ligne par mouvement : un don reçu (colonne Entrée) ou une dépense. Saisissez chaque dépense en € OU en FCFA (une seule des deux colonnes) : la colonne « Dépense retenue » convertit tout en euros avec le taux de l'onglet Listes. Les lignes 7 à 9 sont des exemples à remplacer.
A4: TOTAL ENTRÉES (DONS REÇUS) | C4: TOTAL DÉPENSES (€) | E4: SOLDE ACTUEL (€) | G4: DONT LOGISTIQUE (€) | I4: TOTAL DÉPENSES (FCFA)
A5: =SUM(F7:F306) -> 3200 | C5: =SUM(I7:I306) -> 339.16333 | E5: =SUM(F7:F306)-SUM(I7:I306) -> 2860.8367 | G5: =SUMIF(C7:C306,"Logistique",I7:I306) -> 80 | I5: =SUM(I7:I306)*Listes!$D$5 -> 222476.56
A6: Date | B6: Campagne | C6: Catégorie | D6: Description | E6: N° facture / justificatif | F6: Entrée (€) | G6: Dépense (€) | H6: Dépense (FCFA) | I6: Dépense retenue (€) | J6: Solde cumulé (€)
A7: 45992 | B7: Noël 2025 | C7: Don reçu | D7: Collecte en ligne de décembre | F7: 3200 | I7: =IF(AND(G7="",H7=""),"",IF(G7<>"",G7,H7/Listes!$D$5)) | J7: =IF(AND(F7="",G7="",H7=""),"",SUM(F$7:F7)-SUM(I$7:I7)) -> 3200
A8: 46001 | B8: Noël 2025 | C8: Achats articles | D8: Cahiers, stylos et riz pour l'orphelinat (facture en FCFA) | E8: FACT-2025-001 | H8: 170000 | I8: =IF(AND(G8="",H8=""),"",IF(G8<>"",G8,H8/Listes!$D$5)) -> 259.16333 | J8: =IF(AND(F8="",G8="",H8=""),"",SUM(F$7:F8)-SUM(I$7:I8)) -> 2940.8367
A9: 46003 | B9: Noël 2025 | C9: Logistique | D9: Transport des colis vers Cotonou | E9: FACT-2025-002 | G9: 80 | I9: =IF(AND(G9="",H9=""),"",IF(G9<>"",G9,H9/Listes!$D$5)) -> 80 | J9: =IF(AND(F9="",G9="",H9=""),"",SUM(F$7:F9)-SUM(I$7:I9)) -> 2860.8367
I10: =IF(AND(G10="",H10=""),"",IF(G10<>"",G10,H10/Listes!$D$5)) | J10: =IF(AND(F10="",G10="",H10=""),"",SUM(F$7:F10)-SUM(I$7:I10))
I11: =IF(AND(G11="",H11=""),"",IF(G11<>"",G11,H11/Listes!$D$5)) | J11: =IF(AND(F11="",G11="",H11=""),"",SUM(F$7:F11)-SUM(I$7:I11))
I12: =IF(AND(G12="",H12=""),"",IF(G12<>"",G12,H12/Listes!$D$5)) | J12: =IF(AND(F12="",G12="",H12=""),"",SUM(F$7:F12)-SUM(I$7:I12))
I13: =IF(AND(G13="",H13=""),"",IF(G13<>"",G13,H13/Listes!$D$5)) | J13: =IF(AND(F13="",G13="",H13=""),"",SUM(F$7:F13)-SUM(I$7:I13))
I14: =IF(AND(G14="",H14=""),"",IF(G14<>"",G14,H14/Listes!$D$5)) | J14: =IF(AND(F14="",G14="",H14=""),"",SUM(F$7:F14)-SUM(I$7:I14))
I15: =IF(AND(G15="",H15=""),"",IF(G15<>"",G15,H15/Listes!$D$5)) | J15: =IF(AND(F15="",G15="",H15=""),"",SUM(F$7:F15)-SUM(I$7:I15))
I16: =IF(AND(G16="",H16=""),"",IF(G16<>"",G16,H16/Listes!$D$5)) | J16: =IF(AND(F16="",G16="",H16=""),"",SUM(F$7:F16)-SUM(I$7:I16))
I17: =IF(AND(G17="",H17=""),"",IF(G17<>"",G17,H17/Listes!$D$5)) | J17: =IF(AND(F17="",G17="",H17=""),"",SUM(F$7:F17)-SUM(I$7:I17))
I18: =IF(AND(G18="",H18=""),"",IF(G18<>"",G18,H18/Listes!$D$5)) | J18: =IF(AND(F18="",G18="",H18=""),"",SUM(F$7:F18)-SUM(I$7:I18))
I19: =IF(AND(G19="",H19=""),"",IF(G19<>"",G19,H19/Listes!$D$5)) | J19: =IF(AND(F19="",G19="",H19=""),"",SUM(F$7:F19)-SUM(I$7:I19))
I20: =IF(AND(G20="",H20=""),"",IF(G20<>"",G20,H20/Listes!$D$5)) | J20: =IF(AND(F20="",G20="",H20=""),"",SUM(F$7:F20)-SUM(I$7:I20))
I21: =IF(AND(G21="",H21=""),"",IF(G21<>"",G21,H21/Listes!$D$5)) | J21: =IF(AND(F21="",G21="",H21=""),"",SUM(F$7:F21)-SUM(I$7:I21))
... I306: =IF(AND(G306="",H306=""),"",IF(G306<>"",G306,H306/Listes!$D$5)) | J306: =IF(AND(F306="",G306="",H306=""),"",SUM(F$7:F306)-SUM(I$7:I306))

Sheet Synthèse
A1: SYNTHÈSE PAR CAMPAGNE — ANALYSE COMPARATIVE
A2: Saisissez uniquement la date d'envoi et le « Montant envoyé à la logistique » (colonnes jaunes) : c'est l'enveloppe totale envoyée pour la campagne. La contre-valeur en FCFA et le reste se calculent automatiquement (dons reçus et factures viennent de l'onglet Trésorerie). La dernière ligne donne la clôture de l'année.
A3: Année : | B3: 2026
A5: Campagne | B5: Dons reçus (€) | C5: Date d'envoi | D5: Montant envoyé (€) | E5: Montant envoyé (FCFA) | F5: Factures justifiées (€) | G5: Reste à justifier (€) | H5: Solde campagne (€) | I5: % de l'envoi justifié
A6: =IF(Listes!A5="","",Listes!A5) -> Rentrée scolaire 2025 | B6: =IF($A6="","",SUMIFS(Trésorerie!$F$7:$F$306,Trésorerie!$B$7:$B$306,$A6)) -> 0 | E6: =IF(OR($A6="",D6=""),"",D6*Listes!$D$5) | F6: =IF($A6="","",SUMIFS(Trésorerie!$I$7:$I$306,Trésorerie!$B$7:$B$306,$A6)) -> 0 | G6: =IF(OR($A6="",D6=""),"",D6-F6) | H6: =IF($A6="","",B6-IF(D6="",0,D6)) -> 0 | I6: =IF(OR($A6="",D6="",D6=0),"",F6/D6)
A7: =IF(Listes!A6="","",Listes!A6) -> Noël 2025 | B7: =IF($A7="","",SUMIFS(Trésorerie!$F$7:$F$306,Trésorerie!$B$7:$B$306,$A7)) -> 3200 | C7: 45996 | D7: 3000 | E7: =IF(OR($A7="",D7=""),"",D7*Listes!$D$5) -> 1967871 | F7: =IF($A7="","",SUMIFS(Trésorerie!$I$7:$I$306,Trésorerie!$B$7:$B$306,$A7)) -> 339.16333 | G7: =IF(OR($A7="",D7=""),"",D7-F7) -> 2660.8367 | H7: =IF($A7="","",B7-IF(D7="",0,D7)) -> 200 | I7: =IF(OR($A7="",D7="",D7=0),"",F7/D7) -> 0.11305444
A8: =IF(Listes!A7="","",Listes!A7) -> Pâques 2026 | B8: =IF($A8="","",SUMIFS(Trésorerie!$F$7:$F$306,Trésorerie!$B$7:$B$306,$A8)) -> 0 | E8: =IF(OR($A8="",D8=""),"",D8*Listes!$D$5) | F8: =IF($A8="","",SUMIFS(Trésorerie!$I$7:$I$306,Trésorerie!$B$7:$B$306,$A8)) -> 0 | G8: =IF(OR($A8="",D8=""),"",D8-F8) | H8: =IF($A8="","",B8-IF(D8="",0,D8)) -> 0 | I8: =IF(OR($A8="",D8="",D8=0),"",F8/D8)
A9: =IF(Listes!A8="","",Listes!A8) -> Rentrée scolaire 2026 | B9: =IF($A9="","",SUMIFS(Trésorerie!$F$7:$F$306,Trésorerie!$B$7:$B$306,$A9)) -> 0 | E9: =IF(OR($A9="",D9=""),"",D9*Listes!$D$5) | F9: =IF($A9="","",SUMIFS(Trésorerie!$I$7:$I$306,Trésorerie!$B$7:$B$306,$A9)) -> 0 | G9: =IF(OR($A9="",D9=""),"",D9-F9) | H9: =IF($A9="","",B9-IF(D9="",0,D9)) -> 0 | I9: =IF(OR($A9="",D9="",D9=0),"",F9/D9)
A10: =IF(Listes!A9="","",Listes!A9) -> Noël 2026 | B10: =IF($A10="","",SUMIFS(Trésorerie!$F$7:$F$306,Trésorerie!$B$7:$B$306,$A10)) -> 0 | E10: =IF(OR($A10="",D10=""),"",D10*Listes!$D$5) | F10: =IF($A10="","",SUMIFS(Trésorerie!$I$7:$I$306,Trésorerie!$B$7:$B$306,$A10)) -> 0 | G10: =IF(OR($A10="",D10=""),"",D10-F10) | H10: =IF($A10="","",B10-IF(D10="",0,D10)) -> 0 | I10: =IF(OR($A10="",D10="",D10=0),"",F10/D10)
A11: =IF(Listes!A10="","",Listes!A10) -> Opérations ponctuelles 2026 | B11: =IF($A11="","",SUMIFS(Trésorerie!$F$7:$F$306,Trésorerie!$B$7:$B$306,$A11)) -> 0 | E11: =IF(OR($A11="",D11=""),"",D11*Listes!$D$5) | F11: =IF($A11="","",SUMIFS(Trésorerie!$I$7:$I$306,Trésorerie!$B$7:$B$306,$A11)) -> 0 | G11: =IF(OR($A11="",D11=""),"",D11-F11) | H11: =IF($A11="","",B11-IF(D11="",0,D11)) -> 0 | I11: =IF(OR($A11="",D11="",D11=0),"",F11/D11)
A12: =IF(Listes!A11="","",Listes!A11) | B12: =IF($A12="","",SUMIFS(Trésorerie!$F$7:$F$306,Trésorerie!$B$7:$B$306,$A12)) | E12: =IF(OR($A12="",D12=""),"",D12*Listes!$D$5) | F12: =IF($A12="","",SUMIFS(Trésorerie!$I$7:$I$306,Trésorerie!$B$7:$B$306,$A12)) | G12: =IF(OR($A12="",D12=""),"",D12-F12) | H12: =IF($A12="","",B12-IF(D12="",0,D12)) | I12: =IF(OR($A12="",D12="",D12=0),"",F12/D12)
A13: =IF(Listes!A12="","",Listes!A12) | B13: =IF($A13="","",SUMIFS(Trésorerie!$F$7:$F$306,Trésorerie!$B$7:$B$306,$A13)) | E13: =IF(OR($A13="",D13=""),"",D13*Listes!$D$5) | F13: =IF($A13="","",SUMIFS(Trésorerie!$I$7:$I$306,Trésorerie!$B$7:$B$306,$A13)) | G13: =IF(OR($A13="",D13=""),"",D13-F13) | H13: =IF($A13="","",B13-IF(D13="",0,D13)) | I13: =IF(OR($A13="",D13="",D13=0),"",F13/D13)
A14: =IF(Listes!A13="","",Listes!A13) | B14: =IF($A14="","",SUMIFS(Trésorerie!$F$7:$F$306,Trésorerie!$B$7:$B$306,$A14)) | E14: =IF(OR($A14="",D14=""),"",D14*Listes!$D$5) | F14: =IF($A14="","",SUMIFS(Trésorerie!$I$7:$I$306,Trésorerie!$B$7:$B$306,$A14)) | G14: =IF(OR($A14="",D14=""),"",D14-F14) | H14: =IF($A14="","",B14-IF(D14="",0,D14)) | I14: =IF(OR($A14="",D14="",D14=0),"",F14/D14)
A15: =IF(Listes!A14="","",Listes!A14) | B15: =IF($A15="","",SUMIFS(Trésorerie!$F$7:$F$306,Trésorerie!$B$7:$B$306,$A15)) | E15: =IF(OR($A15="",D15=""),"",D15*Listes!$D$5) | F15: =IF($A15="","",SUMIFS(Trésorerie!$I$7:$I$306,Trésorerie!$B$7:$B$306,$A15)) | G15: =IF(OR($A15="",D15=""),"",D15-F15) | H15: =IF($A15="","",B15-IF(D15="",0,D15)) | I15: =IF(OR($A15="",D15="",D15=0),"",F15/D15)
A16: =IF(Listes!A15="","",Listes!A15) | B16: =IF($A16="","",SUMIFS(Trésorerie!$F$7:$F$306,Trésorerie!$B$7:$B$306,$A16)) | E16: =IF(OR($A16="",D16=""),"",D16*Listes!$D$5) | F16: =IF($A16="","",SUMIFS(Trésorerie!$I$7:$I$306,Trésorerie!$B$7:$B$306,$A16)) | G16: =IF(OR($A16="",D16=""),"",D16-F16) | H16: =IF($A16="","",B16-IF(D16="",0,D16)) | I16: =IF(OR($A16="",D16="",D16=0),"",F16/D16)
A17: =IF(Listes!A16="","",Listes!A16) | B17: =IF($A17="","",SUMIFS(Trésorerie!$F$7:$F$306,Trésorerie!$B$7:$B$306,$A17)) | E17: =IF(OR($A17="",D17=""),"",D17*Listes!$D$5) | F17: =IF($A17="","",SUMIFS(Trésorerie!$I$7:$I$306,Trésorerie!$B$7:$B$306,$A17)) | G17: =IF(OR($A17="",D17=""),"",D17-F17) | H17: =IF($A17="","",B17-IF(D17="",0,D17)) | I17: =IF(OR($A17="",D17="",D17=0),"",F17/D17)
A18: TOTAL — CLÔTURE DE L'ANNÉE | B18: =SUM(B6:B17) -> 3200 | D18: =SUM(D6:D17) -> 3000 | E18: =SUM(E6:E17) -> 1967871 | F18: =SUM(F6:F17) -> 339.16333 | G18: =SUM(G6:G17) -> 2660.8367 | H18: =SUM(H6:H17) -> 200 | I18: =IF(D18=0,"",F18/D18) -> 0.11305444

Sheet Budget
A1: BUDGET ANNUEL PAR POSTE
A2: Modifiez les postes et les budgets (cellules jaunes) à tout moment. Le « Dépensé réel » se calcule automatiquement depuis la Trésorerie (le poste doit porter le même nom que la catégorie).
A3: Année : | B3: 2026
A5: Poste / Catégorie | B5: Budget prévu (€) | C5: Dépensé réel (€) | D5: Écart (€) | E5: % consommé
A6: Achats articles | B6: 1500 | C6: =IF($A6="","",SUMIF(Trésorerie!$C$7:$C$306,$A6,Trésorerie!$I$7:$I$306)) -> 259.16333 | D6: =IF(OR($A6="",B6=""),"",B6-C6) -> 1240.8367 | E6: =IF(OR($A6="",B6="",B6=0),"",C6/B6) -> 0.17277555
A7: Logistique | B7: 300 | C7: =IF($A7="","",SUMIF(Trésorerie!$C$7:$C$306,$A7,Trésorerie!$I$7:$I$306)) -> 80 | D7: =IF(OR($A7="",B7=""),"",B7-C7) -> 220 | E7: =IF(OR($A7="",B7="",B7=0),"",C7/B7) -> 0.26666667
A8: Transport | B8: 200 | C8: =IF($A8="","",SUMIF(Trésorerie!$C$7:$C$306,$A8,Trésorerie!$I$7:$I$306)) -> 0 | D8: =IF(OR($A8="",B8=""),"",B8-C8) -> 200 | E8: =IF(OR($A8="",B8="",B8=0),"",C8/B8) -> 0
A9: Frais divers | B9: 100 | C9: =IF($A9="","",SUMIF(Trésorerie!$C$7:$C$306,$A9,Trésorerie!$I$7:$I$306)) -> 0 | D9: =IF(OR($A9="",B9=""),"",B9-C9) -> 100 | E9: =IF(OR($A9="",B9="",B9=0),"",C9/B9) -> 0
C10: =IF($A10="","",SUMIF(Trésorerie!$C$7:$C$306,$A10,Trésorerie!$I$7:$I$306)) | D10: =IF(OR($A10="",B10=""),"",B10-C10) | E10: =IF(OR($A10="",B10="",B10=0),"",C10/B10)
C11: =IF($A11="","",SUMIF(Trésorerie!$C$7:$C$306,$A11,Trésorerie!$I$7:$I$306)) | D11: =IF(OR($A11="",B11=""),"",B11-C11) | E11: =IF(OR($A11="",B11="",B11=0),"",C11/B11)
C12: =IF($A12="","",SUMIF(Trésorerie!$C$7:$C$306,$A12,Trésorerie!$I$7:$I$306)) | D12: =IF(OR($A12="",B12=""),"",B12-C12) | E12: =IF(OR($A12="",B12="",B12=0),"",C12/B12)
C13: =IF($A13="","",SUMIF(Trésorerie!$C$7:$C$306,$A13,Trésorerie!$I$7:$I$306)) | D13: =IF(OR($A13="",B13=""),"",B13-C13) | E13: =IF(OR($A13="",B13="",B13=0),"",C13/B13)
C14: =IF($A14="","",SUMIF(Trésorerie!$C$7:$C$306,$A14,Trésorerie!$I$7:$I$306)) | D14: =IF(OR($A14="",B14=""),"",B14-C14) | E14: =IF(OR($A14="",B14="",B14=0),"",C14/B14)
C15: =IF($A15="","",SUMIF(Trésorerie!$C$7:$C$306,$A15,Trésorerie!$I$7:$I$306)) | D15: =IF(OR($A15="",B15=""),"",B15-C15) | E15: =IF(OR($A15="",B15="",B15=0),"",C15/B15)
A16: TOTAL | B16: =SUM(B6:B15) -> 2100 | C16: =SUM(C6:C15) -> 339.16333 | D16: =SUM(D6:D15) -> 1760.8367 | E16: =IF(B16=0,"",C16/B16) -> 0.16150635

Sheet Prix
A1: COMPARATIF DES PRIX DES ARTICLES
A2: Notez le prix unitaire de chaque article à chaque campagne (colonnes C à F : les en-têtes jaunes sont modifiables), en € ou en FCFA — gardez la même monnaie sur toute la ligne. L'évolution compare automatiquement le premier prix saisi au dernier. La ligne 6 est un exemple en FCFA.
A5: Article | B5: Unité | C5: Noël 2025 | D5: Pâques 2026 | E5: Rentrée 2026 | F5: Noël 2026 | G5: Évolution | H5: Notes
A6: Sac de riz 25 kg | B6: sac | C6: 11800 | D6: 12800 | G6: =IF(C6="","",IF(F6<>"",(F6-C6)/C6,IF(E6<>"",(E6-C6)/C6,IF(D6<>"",(D6-C6)/C6,"")))) -> 0.084745763
A7: Cahier 96 pages | B7: pièce | G7: =IF(C7="","",IF(F7<>"",(F7-C7)/C7,IF(E7<>"",(E7-C7)/C7,IF(D7<>"",(D7-C7)/C7,""))))
A8: Stylo bleu | B8: pièce | G8: =IF(C8="","",IF(F8<>"",(F8-C8)/C8,IF(E8<>"",(E8-C8)/C8,IF(D8<>"",(D8-C8)/C8,""))))
A9: Cartable | B9: pièce | G9: =IF(C9="","",IF(F9<>"",(F9-C9)/C9,IF(E9<>"",(E9-C9)/C9,IF(D9<>"",(D9-C9)/C9,""))))
A10: Craie blanche | B10: boîte de 100 | G10: =IF(C10="","",IF(F10<>"",(F10-C10)/C10,IF(E10<>"",(E10-C10)/C10,IF(D10<>"",(D10-C10)/C10,""))))
A11: Huile végétale 1 L | B11: bouteille | G11: =IF(C11="","",IF(F11<>"",(F11-C11)/C11,IF(E11<>"",(E11-C11)/C11,IF(D11<>"",(D11-C11)/C11,""))))
A12: Savon | B12: pièce | G12: =IF(C12="","",IF(F12<>"",(F12-C12)/C12,IF(E12<>"",(E12-C12)/C12,IF(D12<>"",(D12-C12)/C12,""))))
G13: =IF(C13="","",IF(F13<>"",(F13-C13)/C13,IF(E13<>"",(E13-C13)/C13,IF(D13<>"",(D13-C13)/C13,""))))
G14: =IF(C14="","",IF(F14<>"",(F14-C14)/C14,IF(E14<>"",(E14-C14)/C14,IF(D14<>"",(D14-C14)/C14,""))))
G15: =IF(C15="","",IF(F15<>"",(F15-C15)/C15,IF(E15<>"",(E15-C15)/C15,IF(D15<>"",(D15-C15)/C15,""))))
G16: =IF(C16="","",IF(F16<>"",(F16-C16)/C16,IF(E16<>"",(E16-C16)/C16,IF(D16<>"",(D16-C16)/C16,""))))
G17: =IF(C17="","",IF(F17<>"",(F17-C17)/C17,IF(E17<>"",(E17-C17)/C17,IF(D17<>"",(D17-C17)/C17,""))))
G18: =IF(C18="","",IF(F18<>"",(F18-C18)/C18,IF(E18<>"",(E18-C18)/C18,IF(D18<>"",(D18-C18)/C18,""))))
G19: =IF(C19="","",IF(F19<>"",(F19-C19)/C19,IF(E19<>"",(E19-C19)/C19,IF(D19<>"",(D19-C19)/C19,""))))
G20: =IF(C20="","",IF(F20<>"",(F20-C20)/C20,IF(E20<>"",(E20-C20)/C20,IF(D20<>"",(D20-C20)/C20,""))))
G21: =IF(C21="","",IF(F21<>"",(F21-C21)/C21,IF(E21<>"",(E21-C21)/C21,IF(D21<>"",(D21-C21)/C21,""))))
G22: =IF(C22="","",IF(F22<>"",(F22-C22)/C22,IF(E22<>"",(E22-C22)/C22,IF(D22<>"",(D22-C22)/C22,""))))
G23: =IF(C23="","",IF(F23<>"",(F23-C23)/C23,IF(E23<>"",(E23-C23)/C23,IF(D23<>"",(D23-C23)/C23,""))))
G24: =IF(C24="","",IF(F24<>"",(F24-C24)/C24,IF(E24<>"",(E24-C24)/C24,IF(D24<>"",(D24-C24)/C24,""))))
G25: =IF(C25="","",IF(F25<>"",(F25-C25)/C25,IF(E25<>"",(E25-C25)/C25,IF(D25<>"",(D25-C25)/C25,""))))

Sheet Dons
A1: DÉTAIL DES DONS PAR CAMPAGNE
A2: Une ligne par article donné : campagne, orphelinat bénéficiaire, article, quantité et valeur. Saisissez le prix unitaire en € OU en FCFA (une seule des deux colonnes) : les valeurs totales se calculent dans les deux monnaies. Les lignes 7 à 9 sont des exemples à remplacer.
A4: VALEUR TOTALE DES DONS (€) | C4: VALEUR TOTALE (FCFA) | E4: ARTICLES DONNÉS (QUANTITÉ)
A5: =SUM(H7:H206) -> 205.21841 | C5: =SUM(H7:H206)*Listes!$D$5 -> 134614.45 | E5: =SUM(E7:E206) -> 122
A6: Campagne | B6: Date | C6: Bénéficiaire (orphelinat…) | D6: Article donné | E6: Quantité | F6: Prix unitaire (€) | G6: Prix unitaire (FCFA) | H6: Valeur totale (€) | I6: Valeur totale (FCFA) | J6: Notes
A7: Noël 2025 | B7: 46011 | C7: Orphelinat Sainte-Marie, Cotonou | D7: Cahier 96 pages | E7: 100 | G7: 330 | H7: =IF(OR(E7="",AND(F7="",G7="")),"",E7*IF(F7<>"",F7,G7/Listes!$D$5)) -> 50.308176 | I7: =IF(H7="","",H7*Listes!$D$5) -> 33000
A8: Noël 2025 | B8: 46011 | C8: Orphelinat Sainte-Marie, Cotonou | D8: Sac de riz 25 kg | E8: 2 | F8: 18 | H8: =IF(OR(E8="",AND(F8="",G8="")),"",E8*IF(F8<>"",F8,G8/Listes!$D$5)) -> 36 | I8: =IF(H8="","",H8*Listes!$D$5) -> 23614.452
A9: Noël 2025 | B9: 46011 | C9: Orphelinat Sainte-Marie, Cotonou | D9: Cartable | E9: 20 | G9: 3900 | H9: =IF(OR(E9="",AND(F9="",G9="")),"",E9*IF(F9<>"",F9,G9/Listes!$D$5)) -> 118.91023 | I9: =IF(H9="","",H9*Listes!$D$5) -> 78000
H10: =IF(OR(E10="",AND(F10="",G10="")),"",E10*IF(F10<>"",F10,G10/Listes!$D$5)) | I10: =IF(H10="","",H10*Listes!$D$5)
H11: =IF(OR(E11="",AND(F11="",G11="")),"",E11*IF(F11<>"",F11,G11/Listes!$D$5)) | I11: =IF(H11="","",H11*Listes!$D$5)
H12: =IF(OR(E12="",AND(F12="",G12="")),"",E12*IF(F12<>"",F12,G12/Listes!$D$5)) | I12: =IF(H12="","",H12*Listes!$D$5)
H13: =IF(OR(E13="",AND(F13="",G13="")),"",E13*IF(F13<>"",F13,G13/Listes!$D$5)) | I13: =IF(H13="","",H13*Listes!$D$5)
H14: =IF(OR(E14="",AND(F14="",G14="")),"",E14*IF(F14<>"",F14,G14/Listes!$D$5)) | I14: =IF(H14="","",H14*Listes!$D$5)
H15: =IF(OR(E15="",AND(F15="",G15="")),"",E15*IF(F15<>"",F15,G15/Listes!$D$5)) | I15: =IF(H15="","",H15*Listes!$D$5)
H16: =IF(OR(E16="",AND(F16="",G16="")),"",E16*IF(F16<>"",F16,G16/Listes!$D$5)) | I16: =IF(H16="","",H16*Listes!$D$5)
H17: =IF(OR(E17="",AND(F17="",G17="")),"",E17*IF(F17<>"",F17,G17/Listes!$D$5)) | I17: =IF(H17="","",H17*Listes!$D$5)
H18: =IF(OR(E18="",AND(F18="",G18="")),"",E18*IF(F18<>"",F18,G18/Listes!$D$5)) | I18: =IF(H18="","",H18*Listes!$D$5)
H19: =IF(OR(E19="",AND(F19="",G19="")),"",E19*IF(F19<>"",F19,G19/Listes!$D$5)) | I19: =IF(H19="","",H19*Listes!$D$5)
H20: =IF(OR(E20="",AND(F20="",G20="")),"",E20*IF(F20<>"",F20,G20/Listes!$D$5)) | I20: =IF(H20="","",H20*Listes!$D$5)
H21: =IF(OR(E21="",AND(F21="",G21="")),"",E21*IF(F21<>"",F21,G21/Listes!$D$5)) | I21: =IF(H21="","",H21*Listes!$D$5)
... H206: =IF(OR(E206="",AND(F206="",G206="")),"",E206*IF(F206<>"",F206,G206/Listes!$D$5)) | I206: =IF(H206="","",H206*Listes!$D$5)

Sheet Listes
A1: LISTES MODIFIABLES
A2: Modifiez ou ajoutez ici vos campagnes et catégories : elles alimentent les menus déroulants et la Synthèse. Ajoutez une campagne à chaque nouvelle collecte.
A4: Campagnes de dons | B4: Catégories de dépenses | D4: Taux de change (1 € = X FCFA)
A5: Rentrée scolaire 2025 | B5: Don reçu | D5: 655.957
A6: Noël 2025 | B6: Achats articles | D6: Taux fixe officiel de l'euro vers le franc CFA (XOF). Modifiable si besoin.
A7: Pâques 2026 | B7: Logistique
A8: Rentrée scolaire 2026 | B8: Transport
A9: Noël 2026 | B9: Frais divers
A10: Opérations ponctuelles 2026 | B10: Autre
